sylajone/__init__.py
sylajone/anasyn.py
sylajone/cache.py
sylajone/cache_pickledb.py
sylajone/refactor.py
sylajone/stemmedsynword.py
sylajone/syn_const.py
sylajone/synnode.py
sylajone-0.3.1.dist-info/DESCRIPTION.rst
sylajone-0.3.1.dist-info/METADATA
sylajone-0.3.1.dist-info/RECORD
sylajone-0.3.1.dist-info/WHEEL
sylajone-0.3.1.dist-info/metadata.json
sylajone-0.3.1.dist-info/top_level.txt
