Metadata-Version: 1.1
Name: sylajone
Version: 0.3.1
Summary: Sylajone: Arabic syntax Analyzer library
Home-page: http://sylajone.sourceforge.net/
Author: Taha Zerrouki
Author-email: taha.zerrouki@gmail.com
License: GPL
Platform: UNKNOWN
Classifier: Development Status :: 5 - Production/Stable
Classifier: Intended Audience :: End Users/Desktop
Classifier: Operating System :: OS Independent
Classifier: Programming Language :: Python
